pdlogger/__init__.py
pdlogger/Logging/AMQPConsumer.py
pdlogger/Logging/AMQPLogger.py
pdlogger/Logging/AMQPLoggingHandler.py
pdlogger/Logging/EnvVarChecker.py
pdlogger/Logging/MysqlDBUtils.py
pdlogger/Logging/__init__.py
pdlogger-0.1.0.dist-info/METADATA
pdlogger-0.1.0.dist-info/WHEEL
pdlogger-0.1.0.dist-info/top_level.txt
pdlogger-0.1.0.dist-info/RECORD
