Metadata-Version: 2.1
Name: pdlogger
Version: 0.1.0
Summary: An example package
Home-page: https://github.com/yourusername/example_package
Author: Maruthi Varaprasad
Author-email: your.email@example.com
Classifier: Programming Language :: Python :: 3
Classifier: License :: OSI Approved :: MIT License
Classifier: Operating System :: OS Independent
Requires-Python: >=3.6
